devicely/__init__.py
devicely/empatica.py
devicely/everion.py
devicely/faros.py
devicely/muse.py
devicely/shimmer_plus.py
devicely/spacelabs.py
devicely/time_stamp.py
devicely-1.1.1.dist-info/LICENSE
devicely-1.1.1.dist-info/WHEEL
devicely-1.1.1.dist-info/METADATA
devicely-1.1.1.dist-info/RECORD
