Metadata-Version: 2.1
Name: devicely
Version: 1.1.1
Summary: Devicely: A Python package for reading, timeshifting and writing sensor data.
Home-page: https://github.com/hpi-dhc/devicely
License: MIT
Author: Ariane Morassi Sasso
Author-email: ariane.morassi-sasso@hpi.de
Requires-Python: >=3.7.1,<4.0.0
Classifier: License :: OSI Approved :: MIT License
Classifier: Programming Language :: Python
Classifier: Programming Language :: Python :: 3
Classifier: Programming Language :: Python :: 3.10
Classifier: Programming Language :: Python :: 3.7
Classifier: Programming Language :: Python :: 3.8
Classifier: Programming Language :: Python :: 3.9
Requires-Dist: importlib-metadata (>=1.0,<2.0); python_version < "3.8"
Requires-Dist: numpy (>=1.21.1,<2.0.0)
Requires-Dist: pandas (>=1.3.0,<2.0.0)
Requires-Dist: pyEDFlib (>=0.1.22,<0.2.0)
Project-URL: Documentation, https://hpi-dhc.github.io/devicely
Project-URL: Repository, https://github.com/hpi-dhc/devicely
